Metadata-Version: 2.1
Name: core-explore-oaipmh-app
Version: 2.19.0
Summary: OAI-PMH exploration functions for curator core project
Home-page: https://github.com/usnistgov/core_explore_oaipmh_app
Author: NIST IT Lab
Author-email: itl_inquiries@nist.gov
License-File: LICENSE.md
